<annotation>
	<folder></folder>
	<filename>569_nl_a133_299_01_jpg.rf.4909955d6eda84649d0139fe5007b054.jpg</filename>
	<path>569_nl_a133_299_01_jpg.rf.4909955d6eda84649d0139fe5007b054.jpg</path>
	<source>
		<database>roboflow.com</database>
	</source>
	<size>
		<width>640</width>
		<height>640</height>
		<depth>3</depth>
	</size>
	<segmented>0</segmented>
	<object>
		<name>line</name>
		<pose>Unspecified</pose>
		<truncated>0</truncated>
		<difficult>0</difficult>
		<occluded>0</occluded>
		<bndbox>
			<xmin>71</xmin>
			<xmax>570</xmax>
			<ymin>47</ymin>
			<ymax>145</ymax>
		</bndbox>
	</object>
	<object>
		<name>line</name>
		<pose>Unspecified</pose>
		<truncated>0</truncated>
		<difficult>0</difficult>
		<occluded>0</occluded>
		<bndbox>
			<xmin>74</xmin>
			<xmax>572</xmax>
			<ymin>157</ymin>
			<ymax>255</ymax>
		</bndbox>
	</object>
	<object>
		<name>line</name>
		<pose>Unspecified</pose>
		<truncated>0</truncated>
		<difficult>0</difficult>
		<occluded>0</occluded>
		<bndbox>
			<xmin>73</xmin>
			<xmax>572</xmax>
			<ymin>247</ymin>
			<ymax>345</ymax>
		</bndbox>
	</object>
	<object>
		<name>line</name>
		<pose>Unspecified</pose>
		<truncated>0</truncated>
		<difficult>0</difficult>
		<occluded>0</occluded>
		<bndbox>
			<xmin>73</xmin>
			<xmax>572</xmax>
			<ymin>356</ymin>
			<ymax>455</ymax>
		</bndbox>
	</object>
	<object>
		<name>line</name>
		<pose>Unspecified</pose>
		<truncated>0</truncated>
		<difficult>0</difficult>
		<occluded>0</occluded>
		<bndbox>
			<xmin>73</xmin>
			<xmax>572</xmax>
			<ymin>472</ymin>
			<ymax>570</ymax>
		</bndbox>
	</object>
</annotation>
